LICENSE.txt
MANIFEST.in
README.rst
setup.py
django_fs_trumbowyg.egg-info/PKG-INFO
django_fs_trumbowyg.egg-info/SOURCES.txt
django_fs_trumbowyg.egg-info/dependency_links.txt
django_fs_trumbowyg.egg-info/top_level.txt
trumbowyg/__init__.py
trumbowyg/forms.py
trumbowyg/models.py
trumbowyg/settings.py
trumbowyg/urls.py
trumbowyg/views.py
trumbowyg/widgets.py
trumbowyg/static/fs_trumbowyg/css/trumbowyg.css
trumbowyg/static/fs_trumbowyg/js/trumbowyg.upload.js
trumbowyg/static/fs_trumbowyg/js/trumbowyg.video.js
trumbowyg/static/fs_trumbowyg/trumbowyg/trumbowyg.js
trumbowyg/static/fs_trumbowyg/trumbowyg/trumbowyg.min.js
trumbowyg/static/fs_trumbowyg/trumbowyg/design/config.rb
trumbowyg/static/fs_trumbowyg/trumbowyg/design/css/trumbowyg.css
trumbowyg/static/fs_trumbowyg/trumbowyg/design/images/icons-2x-s9034954e6d.png
trumbowyg/static/fs_trumbowyg/trumbowyg/design/images/icons-sa75ce98b2b.png
trumbowyg/static/fs_trumbowyg/trumbowyg/design/images/icons/attachement.png
trumbowyg/static/fs_trumbowyg/trumbowyg/design/images/icons/barre.png
trumbowyg/static/fs_trumbowyg/trumbowyg/design/images/icons/bold.png
trumbowyg/static/fs_trumbowyg/trumbowyg/design/images/icons/center-align.png
trumbowyg/static/fs_trumbowyg/trumbowyg/design/images/icons/close.png
trumbowyg/static/fs_trumbowyg/trumbowyg/design/images/icons/formatting.png
trumbowyg/static/fs_trumbowyg/trumbowyg/design/images/icons/fullscreen-exit.png
trumbowyg/static/fs_trumbowyg/trumbowyg/design/images/icons/fullscreen.png
trumbowyg/static/fs_trumbowyg/trumbowyg/design/images/icons/gras.png
trumbowyg/static/fs_trumbowyg/trumbowyg/design/images/icons/horizontal-rule.png
trumbowyg/static/fs_trumbowyg/trumbowyg/design/images/icons/image.png
trumbowyg/static/fs_trumbowyg/trumbowyg/design/images/icons/italic.png
trumbowyg/static/fs_trumbowyg/trumbowyg/design/images/icons/justify-align.png
trumbowyg/static/fs_trumbowyg/trumbowyg/design/images/icons/left-align.png
trumbowyg/static/fs_trumbowyg/trumbowyg/design/images/icons/link.png
trumbowyg/static/fs_trumbowyg/trumbowyg/design/images/icons/ordered-list.png
trumbowyg/static/fs_trumbowyg/trumbowyg/design/images/icons/right-align.png
